curtainutils/__init__.py
curtainutils/client.py
curtainutils/common.py
curtainutils/diann.py
curtainutils/generic.py
curtainutils/msfragger.py
curtainutils/spectronaut.py
curtainutils-0.1.24.dist-info/entry_points.txt
curtainutils-0.1.24.dist-info/licenses/LICENSE
curtainutils-0.1.24.dist-info/METADATA
curtainutils-0.1.24.dist-info/WHEEL
curtainutils-0.1.24.dist-info/RECORD
