Metadata-Version: 2.4
Name: curtainutils
Version: 0.1.24
Summary: A utility package that can be used to upload data to a curtain backend server.
License: MIT
License-File: LICENSE
Author: Toan Phung
Author-email: toan.phung@proteo.info
Requires-Python: >=3.10,<4.0
Classifier: License :: OSI Approved :: MIT License
Classifier: Programming Language :: Python :: 3
Classifier: Programming Language :: Python :: 3.10
Classifier: Programming Language :: Python :: 3.11
Classifier: Programming Language :: Python :: 3.12
Classifier: Programming Language :: Python :: 3.13
Classifier: Programming Language :: Python :: 3.14
Requires-Dist: click (>=8.2.1,<9.0.0)
Requires-Dist: cryptography (>=45.0.5,<46.0.0)
Requires-Dist: openpyxl (>=3.1.5,<4.0.0)
Requires-Dist: pandas (>=2.3.1,<3.0.0)
Requires-Dist: requests (>=2.32.4,<3.0.0)
Requires-Dist: seaborn (>=0.13.1,<0.14.0)
Requires-Dist: sequal (>=2.0.4,<3.0.0)
Requires-Dist: tqdm (>=4.67.1,<5.0.0)
Requires-Dist: uniprotparser (>=1.1.0,<2.0.0)
